xj_invoice/__init__.py
xj_invoice/admin.py
xj_invoice/apps.py
xj_invoice/models.py
xj_invoice/service_register.py
xj_invoice/tests.py
xj_invoice/urls.py
xj_invoice/views.py
xj_invoice/apis/__init__.py
xj_invoice/apis/invoice_apis.py
xj_invoice/apis/invoice_external_apis.py
xj_invoice/apis/invoice_header_apis.py
xj_invoice/apis/invoice_type_apis.py
xj_invoice/apis/middleware.py
xj_invoice/apis/router.py
xj_invoice/services/__init__.py
xj_invoice/services/invoice_extend_service.py
xj_invoice/services/invoice_external_service.py
xj_invoice/services/invoice_header_service.py
xj_invoice/services/invoice_service.py
xj_invoice/services/invoice_type_service.py
xj_invoice/utils/__init__.py
xj_invoice/utils/custom_response.py
xj_invoice/utils/custom_tool.py
xj_invoice/utils/data_permission.py
xj_invoice/utils/j_config.py
xj_invoice/utils/j_dict.py
xj_invoice/utils/join_list.py
xj_invoice/utils/jt.py
xj_invoice/utils/model_handle.py
xj_invoice/utils/user_wrapper.py
xj_invoice/utils/utility_method.py
xj_invoice1/__init__.py
xj_invoice1/admin.py
xj_invoice1/apps.py
xj_invoice1/models.py
xj_invoice1/service_register.py
xj_invoice1/tests.py
xj_invoice1/urls.py
xj_invoice1/views.py
xj_invoice1/apis/__init__.py
xj_invoice1/apis/invoice_apis.py
xj_invoice1/apis/invoice_external_apis.py
xj_invoice1/apis/invoice_header_apis.py
xj_invoice1/apis/invoice_type_apis.py
xj_invoice1/apis/middleware.py
xj_invoice1/apis/router.py
xj_invoice1/services/__init__.py
xj_invoice1/services/invoice_extend_service.py
xj_invoice1/services/invoice_external_service.py
xj_invoice1/services/invoice_header_service.py
xj_invoice1/services/invoice_service.py
xj_invoice1/services/invoice_type_service.py
xj_invoice1/utils/__init__.py
xj_invoice1/utils/custom_response.py
xj_invoice1/utils/custom_tool.py
xj_invoice1/utils/j_config.py
xj_invoice1/utils/j_dict.py
xj_invoice1/utils/join_list.py
xj_invoice1/utils/jt.py
xj_invoice1/utils/model_handle.py
xj_invoice1/utils/user_wrapper.py
xj_invoice-1.0.37.dist-info/METADATA
xj_invoice-1.0.37.dist-info/WHEEL
xj_invoice-1.0.37.dist-info/top_level.txt
xj_invoice-1.0.37.dist-info/RECORD
