Metadata-Version: 2.1
Name: xj-invoice
Version: 1.0.37
Summary: 发票模块
Author: 高栋天
Author-email: 1499593644@qq.com
Maintainer: ['高栋天']
Maintainer-email: angelvy@foxmail.com
License: apache 3.0
